.DS_Store
authorship/__init__.py
authorship/__main__.py
authorship/api.py
authorship/cli.py
authorship/constants.py
authorship/models.py
authorship/py.typed
authorship/version.py
authorship/reader/__init__.py
authorship/reader/google_sheets.py
authorship/reader/obo_sheet.py
authorship/readers/__init__.py
authorship/readers/base.py
authorship/readers/google_sheets.py
authorship/readers/obo_sheet.py
authorship/writer/__init__.py
authorship/writer/biorxiv.py
authorship/writer/nature_scientific_data.py
authorship/writer/text.py
authorship/writers/__init__.py
authorship/writers/base.py
authorship/writers/biorxiv.py
authorship/writers/citation_cff.py
authorship/writers/nature_scientific_data.py
authorship/writers/text.py
authorship-0.1.0.dist-info/LICENSE
authorship-0.1.0.dist-info/METADATA
authorship-0.1.0.dist-info/WHEEL
authorship-0.1.0.dist-info/entry_points.txt
authorship-0.1.0.dist-info/top_level.txt
authorship-0.1.0.dist-info/RECORD
