Metadata-Version: 2.1
Name: authorship
Version: 0.1.0
Summary: Format author lists for academic texts and journal submissions.
Home-page: https://github.com/cthoyt/authorship
Download-URL: https://github.com/cthoyt/authorship/releases
Author: Charles Tapley Hoyt
Author-email: cthoyt@gmail.com
Maintainer: Charles Tapley Hoyt
Maintainer-email: cthoyt@gmail.com
License: MIT
Project-URL: Bug Tracker, https://github.com/cthoyt/authorship/issues
Project-URL: Source Code, https://github.com/cthoyt/authorship
Keywords: snekpack,cookiecutter,publications,academia,bibliometrics,scientometrics
Classifier: Development Status :: 1 - Planning
Classifier: Environment :: Console
Classifier: Intended Audience :: Developers
Classifier: License :: OSI Approved :: MIT License
Classifier: Operating System :: OS Independent
Classifier: Framework :: Pytest
Classifier: Framework :: tox
Classifier: Framework :: Sphinx
Classifier: Programming Language :: Python
Classifier: Programming Language :: Python :: 3.9
Classifier: Programming Language :: Python :: 3.10
Classifier: Programming Language :: Python :: 3 :: Only
Requires-Python: >=3.9
License-File: LICENSE
Requires-Dist: click
Requires-Dist: class-resolver
Requires-Dist: pydantic
Requires-Dist: pandas
Provides-Extra: docs
Requires-Dist: sphinx ; extra == 'docs'
Requires-Dist: sphinx-rtd-theme ; extra == 'docs'
Requires-Dist: sphinx-click ; extra == 'docs'
Requires-Dist: sphinx-autodoc-typehints ; extra == 'docs'
Requires-Dist: sphinx-automodapi ; extra == 'docs'
Provides-Extra: tests
Requires-Dist: pytest ; extra == 'tests'
Requires-Dist: coverage ; extra == 'tests'
